pypx800/__init__.py
pypx800/ainput.py
pypx800/counter.py
pypx800/dinput.py
pypx800/exceptions.py
pypx800/ipx800.py
pypx800/relay.py
pypx800/vainput.py
pypx800/vinput.py
pypx800/voutput.py
pypx800/x4fp.py
pypx800/x4vr.py
pypx800/xdimmer.py
pypx800/xpwm.py
pypx800/xthl.py
pypx800-2.5.1.dist-info/LICENSE
pypx800-2.5.1.dist-info/METADATA
pypx800-2.5.1.dist-info/WHEEL
pypx800-2.5.1.dist-info/top_level.txt
pypx800-2.5.1.dist-info/RECORD
