Metadata-Version: 2.1
Name: pypx800
Version: 2.5.1
Summary: Control the IPX800 and some of its extensions.
Home-page: https://github.com/aohzan/pypx800
Author: Aohzan
Author-email: aohzan@gmail.com
Classifier: Programming Language :: Python :: 3
Classifier: License :: OSI Approved :: MIT License
Classifier: Operating System :: OS Independent
Requires-Python: >=3.11
License-File: LICENSE
